{
    "installation": {
        "installer_command": "npm install"
    },
    "build": {
        "build_script_list": []
    },
    "testing": {
        "markdown:lint": {
            "RUNS_NEW_USER_TESTS": false,
            "timed_out": false,
            "start_time": 1712900091.5001714,
            "end_time": 1712900110.2595232
        },
        "textlint:all": {
            "ERROR": true,
            "RUNS_NEW_USER_TESTS": false,
            "timed_out": false,
            "start_time": 1712900110.25981,
            "end_time": 1712900245.0853498
        },
        "textlint": {
            "RUNS_NEW_USER_TESTS": false,
            "timed_out": false,
            "start_time": 1712900245.0856793,
            "end_time": 1712900268.3259497
        }
    },
    "metadata": {
        "repo_local_dir": "/home/RealWasm/scripts/TESTING_REPO/home-assistant.io"
    }
}