{
    "installation": {
        "installer_command": "npm install"
    },
    "build": {
        "build_script_list": []
    },
    "testing": {
        "test": {
            "num_passing": 2,
            "num_failing": 0,
            "test_infras": [
                "mocha"
            ],
            "timed_out": false,
            "start_time": 1709825693.2462761,
            "end_time": 1709825693.5032349
        }
    },
    "metadata": {
        "repo_local_dir": "/home/michelle/Documents/Work/in-progress/RealWasm/scripts/TESTING_REPO/is-extendable"
    }
}