[
  {
    "url": "https://github.com/Snapmaker/Luban",
    "stars": 384
  },
  {
    "url": "https://github.com/ceajs/cea",
    "stars": 91
  },
  {
    "url": "https://github.com/fvitas/geetest-slider-captcha-solver",
    "stars": 51
  },
  {
    "url": "https://github.com/azu/mumemo",
    "stars": 38
  },
  {
    "url": "https://github.com/ScraperBox-Github/geetest-captcha-solver",
    "stars": 28
  },
  {
    "url": "https://github.com/rrgeorge/EncounterLog",
    "stars": 20
  },
  {
    "url": "https://github.com/Motionline/Piledit-FrontEnd",
    "stars": 8
  },
  {
    "url": "https://github.com/ceajs/slider-captcha",
    "stars": 6
  }
]