[
  {
    "url": "https://github.com/honey-protocol/honey-frontend-legacy",
    "stars": 30
  },
  {
    "url": "https://github.com/gemworks/gem-farm-ui",
    "stars": 30
  },
  {
    "url": "https://github.com/gemworks/transmuter",
    "stars": 26
  },
  {
    "url": "https://github.com/parasol-aser/vrust-open-source",
    "stars": 14
  },
  {
    "url": "https://github.com/gemworks/transmuter-ui",
    "stars": 10
  },
  {
    "url": "https://github.com/honey-protocol/honey-frontend-solana",
    "stars": 9
  },
  {
    "url": "https://github.com/LightYagami200/Animu-Archived",
    "stars": 5
  },
  {
    "url": "https://github.com/UPLukeet/Solana-staking-front-end",
    "stars": 5
  }
]