[
  {
    "url": "https://github.com/HaxeFoundation/haxelib",
    "stars": 164
  },
  {
    "url": "https://github.com/haxiomic/haxe-threejs-template",
    "stars": 26
  },
  {
    "url": "https://github.com/MatthijsKamstra/haxejs",
    "stars": 25
  },
  {
    "url": "https://github.com/giffon/charleywong",
    "stars": 19
  },
  {
    "url": "https://github.com/HaxeFlixel/setup-flixel",
    "stars": 16
  },
  {
    "url": "https://github.com/MatthijsKamstra/haxenode",
    "stars": 13
  },
  {
    "url": "https://github.com/wikiadventure/wikiadventu.re",
    "stars": 11
  },
  {
    "url": "https://github.com/MVCoconut/coconut.storybook",
    "stars": 9
  },
  {
    "url": "https://github.com/MatthijsKamstra/hx-neutralino",
    "stars": 7
  },
  {
    "url": "https://github.com/Jarrio/Haxebot",
    "stars": 7
  },
  {
    "url": "https://github.com/hansagames/practical-shader-dev-hx",
    "stars": 7
  },
  {
    "url": "https://github.com/Kyliathy/haxe-multi-component-project",
    "stars": 5
  }
]