[
  {
    "url": "https://github.com/woocommerce/woocommerce",
    "stars": 9040
  },
  {
    "url": "https://github.com/triggerdotdev/trigger.dev",
    "stars": 6955
  },
  {
    "url": "https://github.com/epicweb-dev/react-fundamentals",
    "stars": 5227
  },
  {
    "url": "https://github.com/marimo-team/marimo",
    "stars": 3807
  },
  {
    "url": "https://github.com/epicweb-dev/advanced-react-patterns",
    "stars": 3343
  },
  {
    "url": "https://github.com/tinyplex/tinybase",
    "stars": 2887
  },
  {
    "url": "https://github.com/epicweb-dev/react-hooks",
    "stars": 2727
  },
  {
    "url": "https://github.com/epicweb-dev/advanced-react-hooks",
    "stars": 1992
  },
  {
    "url": "https://github.com/epicweb-dev/react-performance",
    "stars": 1640
  },
  {
    "url": "https://github.com/skillrecordings/egghead-next",
    "stars": 1382
  },
  {
    "url": "https://github.com/Thinkmill/keystatic",
    "stars": 858
  },
  {
    "url": "https://github.com/epicweb-dev/react-suspense",
    "stars": 795
  },
  {
    "url": "https://github.com/mswjs/examples",
    "stars": 630
  },
  {
    "url": "https://github.com/kodadot/nft-gallery",
    "stars": 572
  },
  {
    "url": "https://github.com/epicweb-dev/full-stack-foundations",
    "stars": 534
  },
  {
    "url": "https://github.com/badass-courses/course-builder",
    "stars": 253
  },
  {
    "url": "https://github.com/epicweb-dev/web-auth",
    "stars": 249
  },
  {
    "url": "https://github.com/statelyai/xstate-tools",
    "stars": 179
  },
  {
    "url": "https://github.com/danielroe/roe.dev",
    "stars": 177
  },
  {
    "url": "https://github.com/epicweb-dev/kcdshop",
    "stars": 176
  },
  {
    "url": "https://github.com/epicweb-dev/web-forms",
    "stars": 165
  },
  {
    "url": "https://github.com/epicweb-dev/full-stack-testing",
    "stars": 162
  },
  {
    "url": "https://github.com/cometkim/espub",
    "stars": 159
  },
  {
    "url": "https://github.com/fireproof-storage/fireproof",
    "stars": 159
  },
  {
    "url": "https://github.com/epicweb-dev/data-modeling",
    "stars": 131
  },
  {
    "url": "https://github.com/spencerc99/playhtml",
    "stars": 128
  },
  {
    "url": "https://github.com/jacobparis-insiders/sly",
    "stars": 114
  },
  {
    "url": "https://github.com/tutors-sdk/tutors",
    "stars": 102
  },
  {
    "url": "https://github.com/barbinbrad/carbon",
    "stars": 99
  },
  {
    "url": "https://github.com/FuelLabs/fuel-explorer",
    "stars": 65
  }
]