[
  {
    "url": "https://github.com/jellyfin/jellyfin-web",
    "stars": 1315
  },
  {
    "url": "https://github.com/ThaUnknown/miru",
    "stars": 897
  },
  {
    "url": "https://github.com/vidstack/player",
    "stars": 864
  },
  {
    "url": "https://github.com/jellyfin/jellyfin-vue",
    "stars": 675
  },
  {
    "url": "https://github.com/ThaUnknown/pwa-haven",
    "stars": 144
  },
  {
    "url": "https://github.com/vesoapp/veso-web",
    "stars": 11
  },
  {
    "url": "https://github.com/Banou26/stub",
    "stars": 7
  },
  {
    "url": "https://github.com/GizmoDevelopment/ramune",
    "stars": 6
  },
  {
    "url": "https://github.com/ClaraCrazy/Sluthub-vue",
    "stars": 5
  },
  {
    "url": "https://github.com/blob03/myJelly",
    "stars": 5
  }
]