[
  {
    "url": "https://github.com/Khan/tota11y",
    "stars": 5040
  },
  {
    "url": "https://github.com/manzinello/mailgo",
    "stars": 1031
  },
  {
    "url": "https://github.com/Uniswap/wallet",
    "stars": 522
  },
  {
    "url": "https://github.com/ng-web-apis/intersection-observer",
    "stars": 155
  },
  {
    "url": "https://github.com/Spyware007/Animating-Buttons",
    "stars": 153
  },
  {
    "url": "https://github.com/SimonSchubert/Braincup",
    "stars": 149
  },
  {
    "url": "https://github.com/cordx56/tweet-generator",
    "stars": 142
  },
  {
    "url": "https://github.com/sanity-io/squizzy",
    "stars": 139
  },
  {
    "url": "https://github.com/stacks-network/blockstack.org",
    "stars": 134
  },
  {
    "url": "https://github.com/ng-web-apis/geolocation",
    "stars": 117
  },
  {
    "url": "https://github.com/ng-web-apis/universal",
    "stars": 117
  },
  {
    "url": "https://github.com/mori-atsushi/insetsx",
    "stars": 114
  },
  {
    "url": "https://github.com/ng-web-apis/resize-observer",
    "stars": 110
  },
  {
    "url": "https://github.com/kunjgit/GameZone",
    "stars": 108
  },
  {
    "url": "https://github.com/hoppscotch/docs",
    "stars": 105
  },
  {
    "url": "https://github.com/Constaline/unblockneteasemusic-desktop",
    "stars": 101
  },
  {
    "url": "https://github.com/dotnet9/Dotnet9",
    "stars": 93
  },
  {
    "url": "https://github.com/ng-web-apis/audio",
    "stars": 88
  },
  {
    "url": "https://github.com/ng-web-apis/canvas",
    "stars": 78
  },
  {
    "url": "https://github.com/ng-web-apis/workers",
    "stars": 64
  },
  {
    "url": "https://github.com/ng-web-apis/payment-request",
    "stars": 63
  },
  {
    "url": "https://github.com/lansuite/lansuite",
    "stars": 60
  },
  {
    "url": "https://github.com/eolinker/apinto-dashboard",
    "stars": 57
  },
  {
    "url": "https://github.com/niieani/gpt-tokenizer",
    "stars": 54
  },
  {
    "url": "https://github.com/kimcore/hcs.js",
    "stars": 49
  },
  {
    "url": "https://github.com/ng-web-apis/storage",
    "stars": 48
  },
  {
    "url": "https://github.com/ng-web-apis/permissions",
    "stars": 47
  },
  {
    "url": "https://github.com/3p3r/cdk-web",
    "stars": 46
  },
  {
    "url": "https://github.com/pathwaycom/pathway-examples",
    "stars": 44
  },
  {
    "url": "https://github.com/zc910704/Vue.js-personal-note",
    "stars": 40
  }
]